LICENSE
py_dtn7/__init__.py
py_dtn7/bundle.py
py_dtn7/dtn_rest_client.py
py_dtn7/dtn_ws_client.py
py_dtn7/utils.py
py_dtn7-0.3.0b1.dist-info/LICENSE
py_dtn7-0.3.0b1.dist-info/METADATA
py_dtn7-0.3.0b1.dist-info/WHEEL
py_dtn7-0.3.0b1.dist-info/RECORD
