Metadata-Version: 2.1
Name: py-dtn7
Version: 0.3.0b1
Summary: 
Home-page: https://github.com/teschmitt/py-dtn7
License: AGPL-3.0-or-later
Author: Lukas Holst
Author-email: lh700@proton.me
Requires-Python: >=3.7,<4.0
Classifier: Development Status :: 4 - Beta
Classifier: Environment :: Console
Classifier: Intended Audience :: Developers
Classifier: License :: OSI Approved :: GNU Affero General Public License v3 or later (AGPLv3+)
Classifier: Natural Language :: English
Classifier: Operating System :: OS Independent
Classifier: Programming Language :: Python :: 3
Classifier: Programming Language :: Python :: 3.7
Classifier: Programming Language :: Python :: 3.8
Classifier: Programming Language :: Python :: 3.9
Classifier: Programming Language :: Python :: 3.10
Classifier: Programming Language :: Python :: 3.11
Classifier: Topic :: Communications
Classifier: Topic :: Software Development :: Libraries
Requires-Dist: cbor2 (>=5.4.3,<6.0.0)
Requires-Dist: requests (>=2.27.1,<3.0.0)
Requires-Dist: websocket-client (>=1.3.2,<2.0.0)
Project-URL: Repository, https://github.com/teschmitt/py-dtn7
